Products.CMFPlacefulWorkflow-3.0.6-py3.13-nspkg.pth
Products/CMFPlacefulWorkflow/DefaultWorkflowPolicy.py
Products/CMFPlacefulWorkflow/PlacefulWorkflowTool.py
Products/CMFPlacefulWorkflow/WorkflowPolicyConfig.py
Products/CMFPlacefulWorkflow/__init__.py
Products/CMFPlacefulWorkflow/adapter.py
Products/CMFPlacefulWorkflow/configure.zcml
Products/CMFPlacefulWorkflow/exportimport.zcml
Products/CMFPlacefulWorkflow/global_symbols.py
Products/CMFPlacefulWorkflow/implements.zcml
Products/CMFPlacefulWorkflow/interfaces.py
Products/CMFPlacefulWorkflow/permissions.py
Products/CMFPlacefulWorkflow/permissions.zcml
Products/CMFPlacefulWorkflow/profiles.zcml
Products/CMFPlacefulWorkflow/setuphandlers.py
Products/CMFPlacefulWorkflow/testing.py
Products/CMFPlacefulWorkflow/tool.gif
Products/CMFPlacefulWorkflow/upgrades.py
Products/CMFPlacefulWorkflow/browser/__init__.py
Products/CMFPlacefulWorkflow/browser/configure.zcml
Products/CMFPlacefulWorkflow/browser/placeful_workflow_configuration.pt
Products/CMFPlacefulWorkflow/browser/placeful_workflow_policy_mapping.pt
Products/CMFPlacefulWorkflow/browser/views.py
Products/CMFPlacefulWorkflow/browser/workflow_policies_controlpanel.pt
Products/CMFPlacefulWorkflow/exportimport/__init__.py
Products/CMFPlacefulWorkflow/exportimport/workflow_policies.py
Products/CMFPlacefulWorkflow/images/workflow_policy.gif
Products/CMFPlacefulWorkflow/profiles/base/componentregistry.xml
Products/CMFPlacefulWorkflow/profiles/base/controlpanel.xml
Products/CMFPlacefulWorkflow/profiles/base/metadata.xml
Products/CMFPlacefulWorkflow/profiles/base/portal_placeful_workflow.xml
Products/CMFPlacefulWorkflow/profiles/base/toolset.xml
Products/CMFPlacefulWorkflow/profiles/default/metadata.xml
Products/CMFPlacefulWorkflow/profiles/default/portal_placeful_workflow.xml
Products/CMFPlacefulWorkflow/profiles/default/rolemap.xml
Products/CMFPlacefulWorkflow/profiles/default/portal_placeful_workflow/intranet.xml
products_cmfplacefulworkflow-3.0.6.dist-info/METADATA
products_cmfplacefulworkflow-3.0.6.dist-info/WHEEL
products_cmfplacefulworkflow-3.0.6.dist-info/namespace_packages.txt
products_cmfplacefulworkflow-3.0.6.dist-info/top_level.txt
products_cmfplacefulworkflow-3.0.6.dist-info/RECORD
